gr_libs/__init__.py
gr_libs/_version.py
gr_libs/all_experiments.py
gr_libs/download_dataset.py
gr_libs/odgr_executor.py
gr_libs/_evaluation/_generate_experiments_results.py
gr_libs/environment/__init__.py
gr_libs/environment/environment.py
gr_libs/environment/_utils/__init__.py
gr_libs/environment/_utils/utils.py
gr_libs/evaluation/__init__.py
gr_libs/evaluation/generate_experiments_results.py
gr_libs/metrics/__init__.py
gr_libs/metrics/metrics.py
gr_libs/ml/__init__.py
gr_libs/ml/agent.py
gr_libs/ml/consts.py
gr_libs/ml/base/__init__.py
gr_libs/ml/base/rl_agent.py
gr_libs/ml/neural/__init__.py
gr_libs/ml/neural/deep_rl_learner.py
gr_libs/ml/neural/utils/__init__.py
gr_libs/ml/neural/utils/dictlist.py
gr_libs/ml/planner/__init__.py
gr_libs/ml/planner/mcts/__init__.py
gr_libs/ml/planner/mcts/mcts_model.py
gr_libs/ml/planner/mcts/_utils/__init__.py
gr_libs/ml/planner/mcts/_utils/node.py
gr_libs/ml/planner/mcts/_utils/tree.py
gr_libs/ml/sequential/__init__.py
gr_libs/ml/sequential/_lstm_model.py
gr_libs/ml/tabular/__init__.py
gr_libs/ml/tabular/state.py
gr_libs/ml/tabular/tabular_q_learner.py
gr_libs/ml/tabular/tabular_rl_agent.py
gr_libs/ml/utils/__init__.py
gr_libs/ml/utils/env.py
gr_libs/ml/utils/format.py
gr_libs/ml/utils/math.py
gr_libs/ml/utils/other.py
gr_libs/ml/utils/storage.py
gr_libs/problems/__init__.py
gr_libs/problems/consts.py
gr_libs/recognizer/__init__.py
gr_libs/recognizer/recognizer.py
gr_libs/recognizer/_utils/__init__.py
gr_libs/recognizer/_utils/format.py
gr_libs/recognizer/gr_as_rl/__init__.py
gr_libs/recognizer/gr_as_rl/gr_as_rl_recognizer.py
gr_libs/recognizer/graml/__init__.py
gr_libs/recognizer/graml/_gr_dataset.py
gr_libs/recognizer/graml/graml_recognizer.py
gr_libs/tutorials/Aura/__init__.py
gr_libs/tutorials/Aura/gcaura_panda_tutorial.py
gr_libs/tutorials/Aura/gcaura_parking_tutorial.py
gr_libs/tutorials/Aura/gcaura_point_maze_tutorial.py
gr_libs/tutorials/Draco/__init__.py
gr_libs/tutorials/Draco/draco_panda_tutorial.py
gr_libs-1.0.3.dist-info/licenses/LICENSE
gr_libs-1.0.3.dist-info/METADATA
gr_libs-1.0.3.dist-info/WHEEL
gr_libs-1.0.3.dist-info/entry_points.txt
gr_libs-1.0.3.dist-info/top_level.txt
gr_libs-1.0.3.dist-info/RECORD
