Metadata-Version: 2.4
Name: gr_libs
Version: 1.0.3
Summary: Package with goal recognition frameworks baselines
Author: Ben Nageris
Author-email: Matan Shamir <matan.shamir@live.biu.ac.il>, Osher Elhadad <osher.elhadad@live.biu.ac.il>
License-Expression: MIT
Classifier: Programming Language :: Python :: 3
Classifier: Operating System :: OS Independent
Requires-Python: >=3.11
License-File: LICENSE
Requires-Dist: gr_envs
Requires-Dist: scipy
Requires-Dist: dill
Requires-Dist: opencv-python
Requires-Dist: tensorboardX
Requires-Dist: torchvision
Requires-Dist: rl_zoo3
Requires-Dist: stable_baselines3[extra]
Requires-Dist: sb3_contrib
Requires-Dist: pytest
Provides-Extra: minigrid
Requires-Dist: gr_envs[minigrid]; extra == "minigrid"
Provides-Extra: highway
Requires-Dist: gr_envs[highway]; extra == "highway"
Provides-Extra: maze
Requires-Dist: gr_envs[maze]; extra == "maze"
Provides-Extra: panda
Requires-Dist: gr_envs[panda]; extra == "panda"
Dynamic: license-file
